Metadata-Version: 2.1
Name: ftpsconnector
Version: 0.2.2
Summary: Initial FTPS Binary File Upload/Dowload connector code for Pensieve
Home-page: http://github.com/bc/ftpsconnector
Author: Brian Cohn
Author-email: brian.cohn@usc.edu
License: MIT
Platform: UNKNOWN
